torchhyper/__init__.py
torchhyper/dataset/__init__.py
torchhyper/dataset/normalizer.py
torchhyper/dataset/toy_datasets.py
torchhyper/model/__init__.py
torchhyper/model/diffusers_unet_2d.py
torchhyper/model/gaussian_mixture_model.py
torchhyper/model/hypernetwork_architectures.py
torchhyper/model/linear_normalizing_flow.py
torchhyper/model/resnet/__init__.py
torchhyper/model/resnet/fid.py
torchhyper/model/resnet/resnet.py
torchhyper/model/vae/__init__.py
torchhyper/model/vae/layers.py
torchhyper/model/vae/loss.py
torchhyper/model/vae/models.py
torchhyper/utils/__init__.py
torchhyper/utils/config.py
torchhyper/utils/custom_lr_decay.py
torchhyper/utils/hyperparam_utils.py
torchhyper/utils/loss_landscape.py
torchhyper/utils/plotting_tools.py
torchhyper/utils/project_path.py
torchhyper/utils/upload_to_dropbox.py
torchhyper-0.1.2.dist-info/LICENSE
torchhyper-0.1.2.dist-info/METADATA
torchhyper-0.1.2.dist-info/WHEEL
torchhyper-0.1.2.dist-info/top_level.txt
torchhyper-0.1.2.dist-info/RECORD
