Metadata-Version: 2.1
Name: torchhyper
Version: 0.1.2
Summary: torchhyper: A PyTorch library for modular hypernetworks
Home-page: https://github.com/alisiahkoohi/torchhyper
Author: Ali Siahkoohi
Author-email: alisk@rice.edu
Classifier: Programming Language :: Python :: 3
Classifier: License :: OSI Approved :: MIT License
Classifier: Operating System :: OS Independent
Requires-Python: <=3.12,>=3.10
License-File: LICENSE
Requires-Dist: matplotlib
Requires-Dist: seaborn
Requires-Dist: numpy
Requires-Dist: tqdm
Requires-Dist: gitpython
Requires-Dist: torch
Provides-Extra: pytorch
Requires-Dist: torch; extra == "pytorch"
Requires-Dist: torch-cuda; extra == "pytorch"
